Mensajes/__init__.py
Mensajes/adios/__init__.py
Mensajes/adios/despedida.py
Mensajes/hola/Saludos.py
Mensajes/hola/__init__.py
tests/__init__.py
tests/test_hola.py
Mensajes_mumanator-6.0.dist-info/LICENSE
Mensajes_mumanator-6.0.dist-info/METADATA
Mensajes_mumanator-6.0.dist-info/WHEEL
Mensajes_mumanator-6.0.dist-info/top_level.txt
Mensajes_mumanator-6.0.dist-info/RECORD
